[{"model": "programs.page", "pk": 1, "fields": {"name": "Page 1", "complete": false, "audio": "http://google.com/audio", "video": "http://google.com/video", "article": "http://google.com/article", "question": "http://google.com/question", "form": "http://google.com/form", "date_created": "2018-11-17T23:53:27.616Z", "date_modified": "2018-11-17T23:53:27.616Z"}}, {"model": "programs.page", "pk": 2, "fields": {"name": "Page 2", "complete": false, "audio": "http://google.com/audio", "video": "http://google.com/video", "article": "http://google.com/article", "question": "http://google.com/question", "form": "http://google.com/form", "date_created": "2018-11-17T23:53:29.649Z", "date_modified": "2018-11-17T23:53:29.649Z"}}, {"model": "programs.page", "pk": 3, "fields": {"name": "Page 3", "complete": false, "audio": "http://google.com/audio", "video": "http://google.com/video", "article": "http://google.com/article", "question": "http://google.com/question", "form": "http://google.com/form", "date_created": "2018-11-17T23:53:31.849Z", "date_modified": "2018-11-17T23:53:31.849Z"}}, {"model": "programs.page", "pk": 4, "fields": {"name": "Page 4", "complete": false, "audio": "http://google.com/audio", "video": "http://google.com/video", "article": "http://google.com/article", "question": "http://google.com/question", "form": "http://google.com/form", "date_created": "2018-11-17T23:53:33.768Z", "date_modified": "2018-11-17T23:53:33.768Z"}}, {"model": "programs.page", "pk": 5, "fields": {"name": "Page 5", "complete": false, "audio": "http://google.com/audio", "video": "http://google.com/video", "article": "http://google.com/article", "question": "http://google.com/question", "form": "http://google.com/form", "date_created": "2018-11-17T23:53:35.891Z", "date_modified": "2018-11-17T23:53:35.891Z"}}, {"model": "programs.page", "pk": 6, "fields": {"name": "Page 6", "complete": false, "audio": "http://google.com/audio", "video": "http://google.com/video", "article": "http://google.com/article", "question": "http://google.com/question", "form": "http://google.com/form", "date_created": "2018-11-17T23:53:37.637Z", "date_modified": "2018-11-17T23:53:37.637Z"}}, {"model": "programs.week", "pk": 1, "fields": {"name": "Week 1", "date_created": "2018-11-17T23:53:48.631Z", "date_modified": "2018-11-17T23:53:48.631Z", "pages": [1, 2]}}, {"model": "programs.week", "pk": 2, "fields": {"name": "Week 2", "date_created": "2018-11-17T23:53:52.523Z", "date_modified": "2018-11-17T23:53:52.523Z", "pages": [2, 3]}}, {"model": "programs.week", "pk": 3, "fields": {"name": "Week 3", "date_created": "2018-11-17T23:54:43.135Z", "date_modified": "2018-11-17T23:54:43.135Z", "pages": [4, 5]}}, {"model": "programs.week", "pk": 4, "fields": {"name": "Week 4", "date_created": "2018-11-17T23:54:49.796Z", "date_modified": "2018-11-17T23:54:49.796Z", "pages": [5, 6]}}, {"model": "programs.program", "pk": 1, "fields": {"name": "Leadership Courses For all", "description": "Lead your company to success", "image": "https://via.placeholder.com/150", "date_created": "2018-11-17T23:56:00.546Z", "date_modified": "2018-11-17T23:56:00.547Z", "progress": 0, "weeks": [1, 2]}}, {"model": "programs.program", "pk": 2, "fields": {"name": "Mindful Communication", "description": "Minfully communicate with coworkers", "image": "https://via.placeholder.com/150", "date_created": "2018-11-17T23:56:25.959Z", "date_modified": "2018-11-17T23:57:34.181Z", "progress": 0, "weeks": [1, 2, 3, 4]}}]